Metadata-Version: 1.1
Name: python-harvest
Version: 1.0.4
Summary: Harvest api client
Home-page: https://github.com/lionheart/python-harvest
Author: Alex Goretoy
Author-email: alex@goretoy.com
License: MIT License
Keywords: harvestapp timetracking api
Platform: UNKNOWN
Classifier: Development Status :: 5 - Production/Stable
Classifier: Environment :: Console
Classifier: Intended Audience :: Developers
Classifier: Natural Language :: English
Classifier: Operating System :: POSIX :: Linux
Classifier: Programming Language :: Python :: 2.7
Classifier: Topic :: Software Development :: Libraries
Classifier: Topic :: Internet :: WWW/HTTP :: Site Management
Classifier: Topic :: Utilities
Classifier: License :: OSI Approved :: MIT License
